cqu_jxgl/__init__.py
cqu_jxgl/exceptions.py
cqu_jxgl/student.py
cqu_jxgl/utils.py
cqu_jxgl/version.py
cqu_jxgl/config/__init__.py
cqu_jxgl/config/config.py
cqu_jxgl/config/config_default.yaml
cqu_jxgl-0.2.0.dist-info/LICENSE
cqu_jxgl-0.2.0.dist-info/METADATA
cqu_jxgl-0.2.0.dist-info/WHEEL
cqu_jxgl-0.2.0.dist-info/top_level.txt
cqu_jxgl-0.2.0.dist-info/RECORD
