Metadata-Version: 2.1
Name: cqu-jxgl
Version: 0.2.0
Summary: 第三方重庆大学教务处登录模块
Home-page: https://github.com/CQU-AI/cqu-jxgl
Author: maxoyed
Author-email: maxoyed@gmail.com
Maintainer: CQU-AI
Maintainer-email: peter@mail.loopy.tech
License: GPL License
Platform: all
Requires-Python: >=3.6
Requires-Dist: requests (>=2.24.0)
Requires-Dist: lxml (>=4.5.2)
Requires-Dist: PyYAML (>=5.3.1)
